server/__init__.py
server/client.py
server/server.py
server/server_gui.py
server/common/__init__.py
server/common/decos.py
server/common/descriptors.py
server/common/errors_user.py
server/common/metaclasses.py
server/common/utils.py
server/common/variables.py
server/logs/__init__.py
server/logs/client_logs_config.py
server/logs/server_logs_config.py
server/server/__init__.py
server/server/add_user.py
server/server/config_window.py
server/server/core.py
server/server/main_window.py
server/server/remove_user.py
server/server/server_database.py
server/server/stat_window.py
server/unit_tests/__init__.py
server/unit_tests/test_client.py
server/unit_tests/test_utils.py
PythonProj_Message_SergeyZ-0.0.1.dist-info/METADATA
PythonProj_Message_SergeyZ-0.0.1.dist-info/WHEEL
PythonProj_Message_SergeyZ-0.0.1.dist-info/top_level.txt
PythonProj_Message_SergeyZ-0.0.1.dist-info/RECORD
